AUTHORS.txt
CHANGES.rst
LICENSE.txt
MANIFEST.in
README.rst
setup.py
calband_django_mobile.egg-info/PKG-INFO
calband_django_mobile.egg-info/SOURCES.txt
calband_django_mobile.egg-info/dependency_links.txt
calband_django_mobile.egg-info/top_level.txt
django_mobile/__init__.py
django_mobile/compat.py
django_mobile/conf.py
django_mobile/context_processors.py
django_mobile/loader.py
django_mobile/middleware.py
django_mobile/models.py
django_mobile/cache/__init__.py
django_mobile/cache/middleware.py