Metadata-Version: 1.1
Name: calband-django-mobile
Version: 0.7.0.dev1
Summary: Detect mobile browsers and serve different template flavours to them.
Home-page: https://github.com/calband/django-mobile
Author: calband
Author-email: calband-compcomm@lists.berkeley.edu
License: BSD
Keywords: django,mobile
Platform: UNKNOWN
Classifier: Development Status :: 4 - Beta
Classifier: Environment :: Web Environment
Classifier: Framework :: Django
Classifier: Intended Audience :: Developers
Classifier: License :: OSI Approved :: BSD License
Classifier: Natural Language :: English
Classifier: Operating System :: OS Independent
Classifier: Programming Language :: Python :: 2.6
Classifier: Programming Language :: Python :: 2.7
Classifier: Programming Language :: Python :: 3.3
Classifier: Topic :: Internet :: WWW/HTTP
Classifier: Topic :: Internet :: WWW/HTTP :: Dynamic Content
Classifier: Topic :: Software Development :: Libraries :: Python Modules
